LICENSE
README.md
pyproject.toml
setup.cfg
setup.py
lyncs_setuptools/__init__.py
lyncs_setuptools/author.py
lyncs_setuptools/classifiers.py
lyncs_setuptools/cmake.py
lyncs_setuptools/data_files.py
lyncs_setuptools/description.py
lyncs_setuptools/packages.py
lyncs_setuptools/pylint.py
lyncs_setuptools/raiseif.py
lyncs_setuptools/setuptools.py
lyncs_setuptools/version.py
lyncs_setuptools.egg-info/PKG-INFO
lyncs_setuptools.egg-info/SOURCES.txt
lyncs_setuptools.egg-info/dependency_links.txt
lyncs_setuptools.egg-info/entry_points.txt
lyncs_setuptools.egg-info/requires.txt
lyncs_setuptools.egg-info/top_level.txt
test/CMakeLists.txt
test/test_all.py