Metadata-Version: 2.1
Name: lyncs-setuptools
Version: 0.3.1
Summary: Setup tools for Lyncs and CMake support
Home-page: https://github.com/Lyncs-API/lyncs.setuptools
Author: Simone Bacchio
Author-email: s.bacchio@gmail.com
License: UNKNOWN
Project-URL: Source, https://github.com/Lyncs-API/lyncs.setuptools
Project-URL: Documentation, https://github.com/Lyncs-API/lyncs.setuptools/README.md
Project-URL: Tracker, https://github.com/Lyncs-API/lyncs.setuptools/issues
Project-URL: Download, https://github.com/Lyncs-API/lyncs.setuptools/archive/master.zip
Keywords: CMake,Lyncs,tools,support,Setup
Platform: UNKNOWN
Classifier: Intended Audience :: Science/Research
Classifier: Operating System :: Unix
Classifier: Topic :: Scientific/Engineering :: Physics
Classifier: Development Status :: 1 - Planning
Classifier: Programming Language :: Python :: 3 :: Only
Classifier: Intended Audience :: Education
Classifier: License :: OSI Approved :: BSD License
Classifier: Intended Audience :: Developers
Classifier: Natural Language :: English
Provides-Extra: test
Provides-Extra: pylint
Provides-Extra: cmake
Provides-Extra: all
License-File: LICENSE
